fioriapps_downloader/__init__.py
fioriapps_downloader/fioriapps_downloader.py
fioriapps_downloader/py.typed
fioriapps_downloader-0.1.1.dist-info/METADATA
fioriapps_downloader-0.1.1.dist-info/WHEEL
fioriapps_downloader-0.1.1.dist-info/licenses/LICENSE
fioriapps_downloader-0.1.1.dist-info/RECORD
